LICENSE
README.md
lyytkimg.py
setup.py
lyytkimg.egg-info/PKG-INFO
lyytkimg.egg-info/SOURCES.txt
lyytkimg.egg-info/dependency_links.txt
lyytkimg.egg-info/requires.txt
lyytkimg.egg-info/top_level.txt